flet_sherpa_onnx/__init__.py
flet_sherpa_onnx/flet_sherpa_onnx.py
flet_sherpa_onnx-0.0.2.dist-info/licenses/LICENSE
flutter/flet_sherpa_onnx/CHANGELOG.md
flutter/flet_sherpa_onnx/LICENSE
flutter/flet_sherpa_onnx/README.md
flutter/flet_sherpa_onnx/analysis_options.yaml
flutter/flet_sherpa_onnx/pubspec.yaml
flutter/flet_sherpa_onnx/lib/flet_sherpa_onnx.dart
flutter/flet_sherpa_onnx/lib/src/extension.dart
flutter/flet_sherpa_onnx/lib/src/fletsherpaonnx.dart
flet_sherpa_onnx-0.0.2.dist-info/METADATA
flet_sherpa_onnx-0.0.2.dist-info/WHEEL
flet_sherpa_onnx-0.0.2.dist-info/top_level.txt
flet_sherpa_onnx-0.0.2.dist-info/RECORD
