Metadata-Version: 2.4
Name: flet-sherpa-onnx
Version: 0.0.2
Summary: FletSherpaOnnx control for Flet
Author-email: SamYuan <yy19902439@126.com>
License-Expression: Apache-2.0
Project-URL: Homepage, https://github.com/SamYuan1990/flet-sherpa-onnx
Project-URL: Documentation, https://github.com/SamYuan1990/flet-sherpa-onnx
Project-URL: Repository, https://github.com/SamYuan1990/flet-sherpa-onnx
Project-URL: Issues, https://github.com/SamYuan1990/flet-sherpa-onnx/issues
Requires-Python: >=3.12
License-File: LICENSE
Requires-Dist: flet>=0.70.0.dev0
Dynamic: license-file
